pyrtitions.py
pyrtitions-0.2.3.dist-info/DESCRIPTION.rst
pyrtitions-0.2.3.dist-info/METADATA
pyrtitions-0.2.3.dist-info/RECORD
pyrtitions-0.2.3.dist-info/WHEEL
pyrtitions-0.2.3.dist-info/entry_points.txt
pyrtitions-0.2.3.dist-info/metadata.json
pyrtitions-0.2.3.dist-info/top_level.txt
