Metadata-Version: 2.0
Name: pyrtitions
Version: 0.2.3
Summary: A small library to get partition information on Linux
Home-page: https://github.com/CRImier/pyrtitions
Author: Arsenijs Picugins
Author-email: crimier@yandex.ru
License: UNKNOWN
Download-URL: https://github.com/CRImier/pyrtitions/archive/0.2.3.tar.gz
Keywords: linux,partitions
Platform: UNKNOWN
